encrypted_json_fields/__init__.py
encrypted_json_fields/fields.py
encrypted_json_fields/helpers.py
encrypted_json_fields/settings.py
encrypted_json_fields/management/__init__.py
encrypted_json_fields/management/utils.py
encrypted_json_fields/management/commands/__init__.py
encrypted_json_fields/management/commands/decrypt_all_tables.py
encrypted_json_fields/management/commands/decrypt_str.py
encrypted_json_fields/management/commands/encrypt_all_tables.py
encrypted_json_fields/management/commands/encrypt_str.py
encrypted_json_fields/management/commands/generate_encryption_key.py
encrypted_json_fields/tests/__init__.py
encrypted_json_fields/tests/test_crypter.py
encrypted_json_fields/tests/test_settings.py
testapp/__init__.py
testapp/admin.py
testapp/models.py
testapp/settings.py
testapp/tests.py
testapp/urls.py
testapp/migrations/0001_initial.py
testapp/migrations/0002_testsearchablemodel_alter_testmodel_id.py
testapp/migrations/0003_alter_testmodel_enc_json_field_alter_testmodel_id.py
testapp/migrations/__init__.py
django_encrypted_json_fields-1.0.5.dist-info/LICENSE
django_encrypted_json_fields-1.0.5.dist-info/METADATA
django_encrypted_json_fields-1.0.5.dist-info/WHEEL
django_encrypted_json_fields-1.0.5.dist-info/top_level.txt
django_encrypted_json_fields-1.0.5.dist-info/RECORD
