Metadata-Version: 2.1
Name: django-encrypted-json-fields
Version: 1.0.5
Summary: A set of fields that wrap standard Django fields, including JSONField, with encryption provided by the python cryptography library
Home-page: https://github.com/morlandi/django-encrypted-json-fields
Author: Mario Orlandi
Author-email: morlandi@brainstorm.it
License: MIT
Classifier: Development Status :: 5 - Production/Stable
Classifier: Operating System :: OS Independent
Classifier: Programming Language :: Python
Classifier: Framework :: Django
Classifier: Intended Audience :: Developers
Classifier: License :: OSI Approved :: BSD License
Classifier: Natural Language :: English
Classifier: Programming Language :: Python :: 3.8
License-File: LICENSE
Requires-Dist: django>=3.1
Requires-Dist: cryptography>=3.4
